helper_func.py
main.py
trivia.py
world_cup.py
pyFIFA-1.0.5.dist-info/LICENSE
pyFIFA-1.0.5.dist-info/METADATA
pyFIFA-1.0.5.dist-info/WHEEL
pyFIFA-1.0.5.dist-info/entry_points.txt
pyFIFA-1.0.5.dist-info/top_level.txt
pyFIFA-1.0.5.dist-info/RECORD
