Metadata-Version: 2.1
Name: pyFIFA
Version: 1.0.5
License-File: LICENSE
Requires-Dist: pyfiglet >=0.8.post1
